<?xml version="1.0" encoding="utf-8"?>
<!DOCTYPE hibernate-mapping PUBLIC "-//Hibernate/Hibernate Mapping DTD 3.0//EN"
"http://hibernate.sourceforge.net/hibernate-mapping-3.0.dtd">
<!-- 
    Mapping file autogenerated by MyEclipse Persistence Tools
-->
<hibernate-mapping>
    <class name="com.gzunicorn.hibernate.infomanager.qualitycheckmanagement.QualityCheckManagement" table="QualityCheckManagement">
        <id name="billno" type="java.lang.String">
            <column name="billno" length="64" />
            <generator class="assigned" />
        </id>
        <property name="maintDivision" type="java.lang.String">
            <column name="MaintDivision" length="64" not-null="true" />
        </property>
        <property name="maintStation" type="java.lang.String">
            <column name="MaintStation" length="64" not-null="true" />
        </property>
        <property name="maintPersonnel" type="java.lang.String">
            <column name="MaintPersonnel" length="64" not-null="true" />
        </property>
        <property name="projectName" type="java.lang.String">
            <column name="projectName" length="512" not-null="true" />
        </property>
        <property name="maintContractNo" type="java.lang.String">
            <column name="MaintContractNo" length="64" not-null="true" />
        </property>
        <property name="elevatorNo" type="java.lang.String">
            <column name="ElevatorNo" length="64" not-null="true" />
        </property>
        <property name="checksPeople" type="java.lang.String">
            <column name="ChecksPeople" length="64" />
        </property>
        <property name="checksDateTime" type="java.lang.String">
            <column name="ChecksDateTime" length="64" />
        </property>
        <property name="totalPoints" type="java.lang.Double">
            <column name="TotalPoints" precision="12" />
        </property>
        <property name="scoreLevel" type="java.lang.String">
            <column name="ScoreLevel" length="64" />
        </property>
        <property name="submitType" type="java.lang.String">
            <column name="SubmitType" length="64" not-null="true" />
        </property>
        <property name="supervOpinion" type="java.lang.String">
            <column name="SupervOpinion" length="1024" />
        </property>
        <property name="partMinisters" type="java.lang.String">
            <column name="PartMinisters" length="64" />
        </property>
        <property name="partMinistersRem" type="java.lang.String">
            <column name="PartMinistersRem" length="1024" />
        </property>
        <property name="remDate" type="java.lang.String">
            <column name="RemDate" length="64" />
        </property>
        <property name="operId" type="java.lang.String">
            <column name="OperId" length="64" not-null="true" />
        </property>
        <property name="operDate" type="java.lang.String">
            <column name="OperDate" length="64" not-null="true" />
        </property>
        <property name="r1" type="java.lang.String">
            <column name="R1" length="64" />
        </property>
        <property name="r2" type="java.lang.String">
            <column name="R2" length="64" />
        </property>
        <property name="r3" type="java.lang.String">
            <column name="R3" length="64" />
        </property>
        <property name="r4" type="java.lang.String">
            <column name="R4" length="512" />
        </property>
        <property name="r5" type="java.lang.String">
            <column name="R5" length="512" />
        </property>
        <property name="r6" type="java.lang.Double">
            <column name="R6" precision="12" />
        </property>
        <property name="r7" type="java.lang.Double">
            <column name="R7" precision="12" />
        </property>
        <property name="r8" type="java.lang.Double">
            <column name="R8" precision="12" />
        </property>
        <property name="r9" type="java.lang.Integer">
            <column name="R9" />
        </property>
        <property name="r10" type="java.lang.Integer">
            <column name="R10" />
        </property>
        <property name="processStatus" type="java.lang.String">
            <column name="ProcessStatus" length="64" />
        </property>
        <property name="salesContractNo" type="java.lang.String">
            <column name="SalesContractNo" length="64" />
        </property>
        <property name="customerSignature" type="java.lang.String">
            <column name="CustomerSignature" length="512" />
        </property>
        <property name="status" type="java.lang.Integer">
            <column name="Status" />
        </property>
        <property name="tokenId" type="java.lang.Long">
            <column name="TokenId" precision="18" scale="0" />
        </property>
        <property name="processName" type="java.lang.String">
            <column name="ProcessName" length="128" />
        </property>
        <property name="superviseId" type="java.lang.String">
            <column name="SuperviseId" length="64" />
        </property>
        <property name="supervisePhone" type="java.lang.String">
            <column name="SupervisePhone" length="64" />
        </property>
        <property name="assessRem" type="java.lang.String">
            <column name="AssessRem" length="1024" />
        </property>
        <property name="deductMoney" type="java.lang.Double">
            <column name="DeductMoney" precision="12" />
        </property>
        <property name="elevatorType" type="java.lang.String">
            <column name="ElevatorType" length="64" />
        </property>
        <property name="personnelPhone" type="java.lang.String">
            <column name="PersonnelPhone" length="64" />
        </property>
        <property name="customerImage" type="java.lang.String">
            <column name="CustomerImage" length="512" />
        </property>
    </class>
</hibernate-mapping>
